{
    "financials": [
        {
            "accountsPayable": 732.8,
            "accountsReceivables": 57.7,
            "accruedLiability": 597.6,
            "accumulatedDepreciation": -1758,
            "additionalPaidInCapital": 90.4,
            "cash": 533.8,
            "cashShortTermInvestments": 533.8,
            "commonStock": 82,
            "currentAssets": 2472.1,
            "currentLiabilities": 2179.6,
            "currentPortionLongTermDebt": 498.8,
            "deferredIncomeTax": 201.9,
            "intangiblesAssets": 538.3,
            "inventory": 1831.7,
            "liabilitiesShareholdersEquity": 6127.4,
            "longTermDebt": 1542.7,
            "longTermInvestments": 305.8,
            "minorityInterest": 5.8,
            "noteReceivableLongTerm": 37.2,
            "otherCurrentAssets": 40.1,
            "otherCurrentliabilities": 350.4,
            "otherEquity": -97.3,
            "otherLiabilities": 8,
            "otherLongTermAssets": 72.2,
            "otherReceivables": 8.799999999999997,
            "period": "2021-04-30",
            "propertyPlantEquipment": 2701.8,
            "retainedEarnings": 2114.3,
            "sharesOutstanding": 63.34542,
            "shortTermDebt": 0,
            "tangibleBookValueperShare": 26.06503,
            "totalAssets": 6127.4,
            "totalDebt": 2041.5,
            "totalEquity": 2189.4,
            "totalLiabilities": 3938,
            "totalReceivables": 66.5,
            "year": 2021
        },
        {
            "accountsPayable": 551.2,
            "accountsReceivables": 49.9,
            "accruedLiability": 543.3,
            "accumulatedDepreciation": -1741.5,
            "additionalPaidInCapital": 90.4,
            "cash": 80.1,
            "cashShortTermInvestments": 80.1,
            "commonStock": 82,
            "currentAssets": 2071,
            "currentLiabilities": 2114.8,
            "currentPortionLongTermDebt": 523.7,
            "deferredIncomeTax": 223.2,
            "intangiblesAssets": 543.2,
            "inventory": 1811.2,
            "liabilitiesShareholdersEquity": 5782.4,
            "longTermDebt": 1672.5,
            "longTermInvestments": 252.3,
            "minorityInterest": 6.2,
            "noteReceivableLongTerm": 4,
            "otherCurrentAssets": 95.4,
            "otherCurrentliabilities": 429.4,
            "otherEquity": -54.5,
            "otherLiabilities": 8.8,
            "otherLongTermAssets": 71.4,
            "otherReceivables": 34.4,
            "period": "2020-04-30",
            "propertyPlantEquipment": 2840.5,
            "retainedEarnings": 1639,
            "sharesOutstanding": 63.33745,
            "shortTermDebt": 67.2,
            "tangibleBookValueperShare": 19.16244,
            "totalAssets": 5782.4,
            "totalDebt": 2263.4,
            "totalEquity": 1756.9,
            "totalLiabilities": 4025.5,
            "totalReceivables": 84.3,
            "year": 2020
        },
        {
            "accountsPayable": 637.3,
            "accountsReceivables": 39,
            "accruedLiability": 545.7,
            "accumulatedDepreciation": -1771.7,
            "additionalPaidInCapital": 90.4,
            "cash": 105,
            "cashShortTermInvestments": 105,
            "commonStock": 82,
            "currentAssets": 2341.7,
            "currentLiabilities": 1824.8,
            "deferredIncomeTax": 187.1,
            "intangiblesAssets": 476.9,
            "inventory": 1987.3,
            "liabilitiesShareholdersEquity": 3976.9,
            "longTermDebt": 0,
            "longTermInvestments": 225.3,
            "minorityInterest": 6.6,
            "noteReceivableLongTerm": 2.1,
            "otherCurrentAssets": 147.70000000000002,
            "otherCurrentliabilities": 358.7,
            "otherEquity": -36.6,
            "otherLiabilities": 17.7,
            "otherLongTermAssets": 19.3,
            "otherReceivables": 62.7,
            "period": "2019-04-30",
            "propertyPlantEquipment": 911.6,
            "retainedEarnings": 1804.9,
            "sharesOutstanding": 63.21779,
            "shortTermDebt": 283.1,
            "tangibleBookValueperShare": 23.15487,
            "totalAssets": 3976.9,
            "totalDebt": 283.1,
            "totalEquity": 1940.7,
            "totalLiabilities": 2036.2,
            "totalReceivables": 101.7,
            "year": 2019
        },
        {
            "accountsPayable": 881.6,
            "accountsReceivables": 33.7,
            "accruedLiability": 536.5,
            "accumulatedDepreciation": -1688.1,
            "additionalPaidInCapital": 90.4,
            "cash": 115.8,
            "cashShortTermInvestments": 115.8,
            "commonStock": 82,
            "currentAssets": 2490.7,
            "currentLiabilities": 1708.4,
            "deferredIncomeTax": 210.1,
            "intangiblesAssets": 428.2,
            "inventory": 2038,
            "liabilitiesShareholdersEquity": 4199.7,
            "longTermDebt": 0,
            "longTermInvestments": 224.5,
            "noteReceivableLongTerm": 1.5,
            "otherCurrentAssets": 206.5,
            "otherCurrentliabilities": 290.3,
            "otherEquity": -44.9,
            "otherLiabilities": 17.3,
            "otherLongTermAssets": 13.5,
            "otherReceivables": 96.7,
            "period": "2018-04-30",
            "propertyPlantEquipment": 1041.3,
            "retainedEarnings": 2136.4,
            "sharesOutstanding": 63.20814,
            "shortTermDebt": 0,
            "tangibleBookValueperShare": 29.04215,
            "totalAssets": 4199.7,
            "totalDebt": 0,
            "totalEquity": 2263.9,
            "totalLiabilities": 1935.8,
            "totalReceivables": 130.4,
            "year": 2018
        },
        {
            "accountsPayable": 635.2,
            "accountsReceivables": 31,
            "accruedLiability": 500.2,
            "accumulatedDepreciation": -1480.5,
            "additionalPaidInCapital": 90.4,
            "cash": 625.1,
            "cashShortTermInvestments": 625.1,
            "commonStock": 82,
            "currentAssets": 2476.4,
            "currentLiabilities": 1421.9,
            "deferredIncomeTax": 195.8,
            "intangiblesAssets": 340.2,
            "inventory": 1630.7,
            "liabilitiesShareholdersEquity": 3899.4,
            "longTermDebt": 0,
            "noteReceivableLongTerm": 1.5,
            "otherCurrentAssets": 158.29999999999998,
            "otherCurrentliabilities": 286.5,
            "otherEquity": -89.9,
            "otherLiabilities": 31,
            "otherLongTermAssets": 17,
            "otherReceivables": 31.299999999999997,
            "period": "2017-04-30",
            "propertyPlantEquipment": 1064.3,
            "retainedEarnings": 2168.2,
            "sharesOutstanding": 63.08344,
            "shortTermDebt": 0,
            "tangibleBookValueperShare": 30.28529,
            "totalAssets": 3899.4,
            "totalDebt": 0,
            "totalEquity": 2250.7,
            "totalLiabilities": 1648.7,
            "totalReceivables": 62.3,
            "year": 2017
        },
        {
            "accountsPayable": 685.7,
            "accountsReceivables": 30.5,
            "accruedLiability": 528.9,
            "accumulatedDepreciation": -1410.4,
            "additionalPaidInCapital": 90.4,
            "cash": 604.3,
            "cashShortTermInvestments": 604.3,
            "commonStock": 82,
            "currentAssets": 2506.9,
            "currentLiabilities": 1588.9,
            "deferredIncomeTax": 190.2,
            "intangiblesAssets": 270.6,
            "inventory": 1639.2,
            "liabilitiesShareholdersEquity": 3922.8,
            "longTermDebt": 0,
            "noteReceivableLongTerm": 1.2,
            "otherCurrentAssets": 140.1,
            "otherCurrentliabilities": 374.3,
            "otherEquity": -132.9,
            "otherLiabilities": 4.9,
            "otherLongTermAssets": 16.9,
            "otherReceivables": 92.8,
            "period": "2016-04-30",
            "propertyPlantEquipment": 1127.2,
            "retainedEarnings": 2099.3,
            "sharesOutstanding": 63.37642,
            "shortTermDebt": 0,
            "tangibleBookValueperShare": 29.47784,
            "totalAssets": 3922.8,
            "totalDebt": 0,
            "totalEquity": 2138.8,
            "totalLiabilities": 1784,
            "totalReceivables": 123.3,
            "year": 2016
        }
    ],
    "symbol": "CLAS B.ST"
}