{
    "financials": [
        {
            "accountsPayable": 204,
            "accountsReceivables": 219,
            "accruedLiability": 141,
            "accumulatedDepreciation": -1617,
            "additionalPaidInCapital": 730,
            "cash": 330,
            "cashShortTermInvestments": 330,
            "commonStock": 153,
            "currentAssets": 972,
            "currentLiabilities": 395,
            "deferredIncomeTax": 105,
            "intangiblesAssets": 9,
            "inventory": 355,
            "liabilitiesShareholdersEquity": 2257,
            "longTermDebt": 411,
            "longTermInvestments": 50,
            "otherAssets": 21,
            "otherCurrentAssets": 23,
            "otherCurrentliabilities": 50,
            "otherEquity": 9,
            "otherLiabilities": 45,
            "otherLongTermAssets": 2,
            "otherReceivables": 45,
            "period": "2020-12-31",
            "propertyPlantEquipment": 1203,
            "retainedEarnings": 478,
            "sharesOutstanding": 152.57193,
            "shortTermDebt": 0,
            "tangibleBookValueperShare": 8.3305,
            "totalAssets": 2257,
            "totalDebt": 411,
            "totalEquity": 1301,
            "totalLiabilities": 956,
            "totalReceivables": 264,
            "treasuryStock": -69,
            "year": 2020
        },
        {
            "accountsPayable": 202,
            "accountsReceivables": 269,
            "accruedLiability": 167,
            "accumulatedDepreciation": -1512,
            "additionalPaidInCapital": 730,
            "cash": 376,
            "cashShortTermInvestments": 376,
            "commonStock": 153,
            "currentAssets": 1093,
            "currentLiabilities": 406,
            "deferredIncomeTax": 135,
            "intangiblesAssets": 13,
            "inventory": 375,
            "liabilitiesShareholdersEquity": 2373,
            "longTermDebt": 411,
            "longTermInvestments": 49,
            "otherCurrentAssets": 41,
            "otherCurrentliabilities": 37,
            "otherEquity": 38,
            "otherLiabilities": 41,
            "otherLongTermAssets": 20,
            "otherReceivables": 32,
            "period": "2019-12-31",
            "propertyPlantEquipment": 1198,
            "retainedEarnings": 528,
            "sharesOutstanding": 152.57193,
            "shortTermDebt": 0,
            "tangibleBookValueperShare": 8.95971,
            "totalAssets": 2373,
            "totalDebt": 411,
            "totalEquity": 1380,
            "totalLiabilities": 993,
            "totalReceivables": 301,
            "treasuryStock": -69,
            "year": 2019
        },
        {
            "accountsPayable": 174,
            "accountsReceivables": 339,
            "accruedLiability": 188,
            "accumulatedDepreciation": -1416,
            "additionalPaidInCapital": 730,
            "cash": 238,
            "cashShortTermInvestments": 238,
            "commonStock": 153,
            "currentAssets": 1111,
            "currentLiabilities": 409,
            "deferredIncomeTax": 119,
            "intangiblesAssets": 17,
            "inventory": 389,
            "liabilitiesShareholdersEquity": 2401,
            "longTermDebt": 395,
            "longTermInvestments": 25,
            "otherCurrentAssets": 86,
            "otherCurrentliabilities": 47,
            "otherEquity": 98,
            "otherLiabilities": 18,
            "otherLongTermAssets": 69,
            "otherReceivables": 59,
            "period": "2018-12-31",
            "propertyPlantEquipment": 1179,
            "retainedEarnings": 548,
            "sharesOutstanding": 152.57193,
            "shortTermDebt": 0,
            "tangibleBookValueperShare": 9.45783,
            "totalAssets": 2401,
            "totalDebt": 395,
            "totalEquity": 1460,
            "totalLiabilities": 941,
            "totalReceivables": 398,
            "treasuryStock": -69,
            "year": 2018
        },
        {
            "accountsPayable": 149,
            "accountsReceivables": 260,
            "accruedLiability": 155,
            "accumulatedDepreciation": -1332,
            "additionalPaidInCapital": 730,
            "cash": 326,
            "cashShortTermInvestments": 326,
            "commonStock": 153,
            "currentAssets": 929,
            "currentLiabilities": 354,
            "currentPortionLongTermDebt": 0,
            "deferredIncomeTax": 42,
            "intangiblesAssets": 19,
            "inventory": 279,
            "liabilitiesShareholdersEquity": 2007,
            "longTermDebt": 394,
            "longTermInvestments": 16,
            "otherCurrentAssets": 19,
            "otherCurrentliabilities": 50,
            "otherEquity": 10,
            "otherLiabilities": 10,
            "otherLongTermAssets": 23,
            "otherReceivables": 45,
            "period": "2017-12-31",
            "propertyPlantEquipment": 1020,
            "retainedEarnings": 383,
            "sharesOutstanding": 152.57193,
            "shortTermDebt": 0,
            "tangibleBookValueperShare": 7.78649,
            "totalAssets": 2007,
            "totalDebt": 394,
            "totalEquity": 1207,
            "totalLiabilities": 800,
            "totalReceivables": 305,
            "treasuryStock": -69,
            "year": 2017
        },
        {
            "accountsPayable": 152,
            "accountsReceivables": 207,
            "accruedLiability": 127,
            "accumulatedDepreciation": -1244,
            "additionalPaidInCapital": 730,
            "cash": 16,
            "cashShortTermInvestments": 16,
            "commonStock": 153,
            "currentAssets": 584,
            "currentLiabilities": 324,
            "currentPortionLongTermDebt": 14,
            "deferredIncomeTax": 8,
            "intangiblesAssets": 10,
            "inventory": 278,
            "liabilitiesShareholdersEquity": 1489,
            "longTermDebt": 0,
            "longTermInvestments": 13,
            "otherCurrentAssets": 37,
            "otherCurrentliabilities": 31,
            "otherLiabilities": 6,
            "otherLongTermAssets": 0,
            "otherReceivables": 46,
            "period": "2016-12-31",
            "propertyPlantEquipment": 882,
            "retainedEarnings": 337,
            "sharesOutstanding": 152.57193,
            "shortTermDebt": 0,
            "tangibleBookValueperShare": 7.47844,
            "totalAssets": 1489,
            "totalDebt": 14,
            "totalEquity": 1151,
            "totalLiabilities": 338,
            "totalReceivables": 253,
            "treasuryStock": -69,
            "year": 2016
        },
        {
            "accountsPayable": 129,
            "accountsReceivables": 193,
            "accruedLiability": 131,
            "accumulatedDepreciation": -1207,
            "additionalPaidInCapital": 730,
            "cash": 169,
            "cashShortTermInvestments": 169,
            "commonStock": 153,
            "currentAssets": 680,
            "currentLiabilities": 310,
            "intangiblesAssets": 7,
            "inventory": 267,
            "liabilitiesShareholdersEquity": 1386,
            "longTermDebt": 0,
            "longTermInvestments": 2,
            "otherCurrentAssets": 11,
            "otherCurrentliabilities": 50,
            "otherLiabilities": 18,
            "otherLongTermAssets": 38,
            "otherReceivables": 40,
            "period": "2015-12-31",
            "propertyPlantEquipment": 659,
            "retainedEarnings": 244,
            "sharesOutstanding": 152.57193,
            "shortTermDebt": 0,
            "tangibleBookValueperShare": 6.88855,
            "totalAssets": 1386,
            "totalDebt": 0,
            "totalEquity": 1058,
            "totalLiabilities": 328,
            "totalReceivables": 233,
            "treasuryStock": -69,
            "year": 2015
        },
        {
            "accountsPayable": 104,
            "accountsReceivables": 184,
            "accruedLiability": 122,
            "accumulatedDepreciation": -1150,
            "cash": 89,
            "cashShortTermInvestments": 89,
            "commonStock": 153,
            "currentAssets": 570,
            "currentLiabilities": 247,
            "currentPortionLongTermDebt": 0,
            "intangiblesAssets": 5,
            "inventory": 255,
            "liabilitiesShareholdersEquity": 1261,
            "longTermDebt": 30,
            "noteReceivableLongTerm": 2,
            "otherCurrentAssets": 15,
            "otherCurrentliabilities": 21,
            "otherEquity": 730,
            "otherLiabilities": 9,
            "otherLongTermAssets": 69,
            "otherReceivables": 27,
            "period": "2014-12-31",
            "propertyPlantEquipment": 615,
            "retainedEarnings": 161,
            "sharesOutstanding": 152.6,
            "shortTermDebt": 0,
            "tangibleBookValueperShare": 6.3565,
            "totalAssets": 1261,
            "totalDebt": 30,
            "totalEquity": 975,
            "totalLiabilities": 286,
            "totalReceivables": 211,
            "treasuryStock": -69,
            "year": 2014
        },
        {
            "accountsPayable": 116,
            "accountsReceivables": 127,
            "accruedLiability": 112,
            "accumulatedDepreciation": -1329,
            "cash": 35,
            "cashShortTermInvestments": 35,
            "commonStock": 153,
            "currentAssets": 455,
            "currentLiabilities": 323,
            "currentPortionLongTermDebt": 60,
            "intangiblesAssets": 5,
            "inventory": 246,
            "liabilitiesShareholdersEquity": 1161,
            "longTermDebt": 0,
            "longTermInvestments": 1,
            "otherCurrentAssets": 10,
            "otherCurrentliabilities": 35,
            "otherEquity": 730,
            "otherLiabilities": 13,
            "otherLongTermAssets": 53,
            "otherReceivables": 37,
            "period": "2013-12-31",
            "propertyPlantEquipment": 647,
            "retainedEarnings": 11,
            "sharesOutstanding": 152.6,
            "shortTermDebt": 0,
            "tangibleBookValueperShare": 5.3735,
            "totalAssets": 1161,
            "totalDebt": 60,
            "totalEquity": 825,
            "totalLiabilities": 336,
            "totalReceivables": 164,
            "treasuryStock": -69,
            "year": 2013
        },
        {
            "accountsPayable": 76,
            "accountsReceivables": 157,
            "accruedLiability": 110,
            "accumulatedDepreciation": -1185,
            "cash": 26,
            "cashShortTermInvestments": 26,
            "commonStock": 153,
            "currentAssets": 485,
            "currentLiabilities": 286,
            "currentPortionLongTermDebt": 78,
            "intangiblesAssets": 4,
            "inventory": 240,
            "liabilitiesShareholdersEquity": 1294,
            "longTermDebt": 0,
            "otherCurrentAssets": 21,
            "otherCurrentliabilities": 22,
            "otherEquity": 708,
            "otherLiabilities": 15,
            "otherLongTermAssets": 50,
            "otherReceivables": 41,
            "period": "2012-12-31",
            "propertyPlantEquipment": 755,
            "retainedEarnings": 201,
            "sharesOutstanding": 152.6,
            "shortTermDebt": 0,
            "tangibleBookValueperShare": 6.481,
            "totalAssets": 1294,
            "totalDebt": 78,
            "totalEquity": 993,
            "totalLiabilities": 301,
            "totalReceivables": 198,
            "treasuryStock": -69,
            "year": 2012
        },
        {
            "accountsPayable": 119,
            "accountsReceivables": 125,
            "accruedLiability": 112,
            "accumulatedDepreciation": -1066,
            "cashEquivalents": 21,
            "cashShortTermInvestments": 22,
            "commonStock": 153,
            "currentAssets": 506,
            "currentLiabilities": 317,
            "currentPortionLongTermDebt": 5,
            "intangiblesAssets": 3,
            "inventory": 276,
            "liabilitiesShareholdersEquity": 1347,
            "longTermDebt": 5,
            "noteReceivableLongTerm": 5,
            "otherCurrentAssets": 30,
            "otherCurrentliabilities": 44,
            "otherEquity": 730,
            "otherLiabilities": 11,
            "otherLongTermAssets": 73,
            "otherReceivables": 53,
            "period": "2011-12-31",
            "propertyPlantEquipment": 760,
            "retainedEarnings": 200,
            "sharesOutstanding": 152.6,
            "shortTermDebt": 37,
            "shortTermInvestments": 1,
            "tangibleBookValueperShare": 6.6252,
            "totalAssets": 1347,
            "totalDebt": 47,
            "totalEquity": 1014,
            "totalLiabilities": 333,
            "totalReceivables": 178,
            "treasuryStock": -69,
            "year": 2011
        }
    ],
    "symbol": "RROS.ST"
}