{
    "metric": {
        "_10DayAverageTradingVolume": 0.28345,
        "_13WeekPriceReturnDaily": -10.10526,
        "_26WeekPriceReturnDaily": -34.00309,
        "_3MonthAverageTradingVolume": 10.37309,
        "_52WeekHigh": 21,
        "_52WeekHighDate": "2020-09-03",
        "_52WeekLow": 8.36,
        "_52WeekLowDate": "2021-07-15",
        "_52WeekPriceReturnDaily": -36.07784,
        "_5DayPriceReturnDaily": -1.49942,
        "_assetTurnoverAnnual": 0.36561,
        "_assetTurnoverTTM": 0.37102,
        "_beta": 1.08425,
        "_bookValuePerShareAnnual": 2.5899,
        "_bookValuePerShareQuarterly": 2.47707,
        "_bookValueShareGrowth5Y": 34.44296,
        "_capitalSpendingGrowth5Y": -8.78576,
        "_cashFlowPerShareAnnual": -0.56869,
        "_cashFlowPerShareTTM": -0.50208,
        "_cashPerSharePerShareAnnual": 2.82344,
        "_cashPerSharePerShareQuarterly": 2.74758,
        "_currentDividendYieldTTM": 0,
        "_currentEvfreeCashFlowAnnual": null,
        "_currentEvfreeCashFlowTTM": null,
        "_currentRatioAnnual": 3.96567,
        "_currentRatioQuarterly": 3.77919,
        "_dividendGrowthRate5Y": null,
        "_dividendPerShare5Y": 0,
        "_dividendPerShareAnnual": 0,
        "_dividendYield5Y": 0,
        "_dividendYieldIndicatedAnnual": null,
        "_dividendsPerShareTTM": 0,
        "_ebitdPerShareTTM": -0.4605,
        "_ebitdaCagr5Y": null,
        "_ebitdaInterimCagr5Y": null,
        "_epsBasicExclExtraItemsAnnual": -0.64,
        "_epsBasicExclExtraItemsTTM": -0.61209,
        "_epsExclExtraItemsAnnual": -0.64,
        "_epsExclExtraItemsTTM": -0.61209,
        "_epsGrowth3Y": null,
        "_epsGrowth5Y": null,
        "_epsGrowthQuarterlyYoy": 54.76667,
        "_epsGrowthTTMYoy": 41.466,
        "_epsInclExtraItemsAnnual": -0.64,
        "_epsInclExtraItemsTTM": -0.61209,
        "_epsNormalizedAnnual": -0.65798,
        "_focfCagr5Y": null,
        "_freeCashFlowAnnual": -39.876,
        "_freeCashFlowPerShareTTM": -0.31691,
        "_freeCashFlowTTM": -38.283,
        "_freeOperatingCashFlowrevenue5Y": -66.78796,
        "_freeOperatingCashFlowrevenueTTM": -29.58844,
        "_grossMargin5Y": 90.18054,
        "_grossMarginAnnual": 95.35785,
        "_grossMarginTTM": 95.27148,
        "_inventoryTurnoverAnnual": null,
        "_inventoryTurnoverTTM": null,
        "_longTermDebtequityAnnual": 1.93862,
        "_longTermDebtequityQuarterly": 1.90956,
        "_marketCapitalization": 1189.79,
        "_monthToDatePriceReturnDaily": -7.77538,
        "_netDebtAnnual": -385.584,
        "_netDebtInterim": -376.202,
        "_netIncomeEmployeeAnnual": -438659.6,
        "_netIncomeEmployeeTTM": -404703.5,
        "_netInterestCoverageAnnual": -8.72719,
        "_netInterestCoverageTTM": -13.27291,
        "_netMarginGrowth5Y": null,
        "_netProfitMargin5Y": -78.69762,
        "_netProfitMarginAnnual": -60.30699,
        "_netProfitMarginTTM": -53.7999,
        "_operatingMargin5Y": -78.33375,
        "_operatingMarginAnnual": -53.53097,
        "_operatingMarginTTM": -49.91769,
        "_payoutRatioAnnual": null,
        "_payoutRatioTTM": null,
        "_pbAnnual": 3.29742,
        "_pbQuarterly": 3.44762,
        "_pcfShareTTM": null,
        "_peBasicExclExtraTTM": null,
        "_peExclExtraAnnual": null,
        "_peExclExtraHighTTM": null,
        "_peExclExtraTTM": null,
        "_peExclLowTTM": null,
        "_peInclExtraTTM": null,
        "_peNormalizedAnnual": null,
        "_pfcfShareAnnual": null,
        "_pfcfShareTTM": null,
        "_pretaxMargin5Y": -78.97087,
        "_pretaxMarginAnnual": -60.26458,
        "_pretaxMarginTTM": -53.67778,
        "_priceRelativeToSP50013Week": null,
        "_priceRelativeToSP50026Week": null,
        "_priceRelativeToSP5004Week": null,
        "_priceRelativeToSP50052Week": null,
        "_priceRelativeToSP500Ytd": null,
        "_psAnnual": 8.70067,
        "_psTTM": 9.19573,
        "_ptbvAnnual": 3.65731,
        "_ptbvQuarterly": 3.83206,
        "_quickRatioAnnual": null,
        "_quickRatioQuarterly": null,
        "_receivablesTurnoverAnnual": 2.64036,
        "_receivablesTurnoverTTM": 3.16662,
        "_revenueEmployeeAnnual": 727377.7,
        "_revenueEmployeeTTM": 752238.4,
        "_revenueGrowth3Y": 18.29753,
        "_revenueGrowth5Y": 50.17694,
        "_revenueGrowthQuarterlyYoy": -20.54531,
        "_revenueGrowthTTMYoy": -5.67681,
        "_revenuePerShareAnnual": 1.06124,
        "_revenuePerShareTTM": 1.07105,
        "_revenueShareGrowth5Y": 37.35542,
        "_roaRfy": -22.04868,
        "_roaa5Y": -34.55391,
        "_roae5Y": -50.62628,
        "_roaeTTM": -30.10325,
        "_roeRfy": -32.15014,
        "_roeTTM": -19.96071,
        "_roi5Y": -50.1813,
        "_roiAnnual": -31.51158,
        "_roiTTM": -29.46431,
        "_tangibleBookValuePerShareAnnual": 2.33505,
        "_tangibleBookValuePerShareQuarterly": 2.22857,
        "_tbvCagr5Y": 45.71953,
        "_totalDebtCagr5Y": null,
        "_totalDebttotalEquityAnnual": 2.15534,
        "_totalDebttotalEquityQuarterly": 1.90956,
        "_yearToDatePriceReturnDaily": -39.51841
    },
    "metricType": "all",
    "series": {
        "annual": {
            "cashRatio": [
                {
                    "period": "2019-12-31",
                    "v": 0.8283788350069746
                },
                {
                    "period": "2018-12-31",
                    "v": 2.4178560168155543
                },
                {
                    "period": "2017-12-31",
                    "v": 0.3791860506410029
                },
                {
                    "period": "2016-12-31",
                    "v": 0.3167619728377412
                },
                {
                    "period": "2015-12-31",
                    "v": 0.8272278071221675
                },
                {
                    "period": "2014-12-31",
                    "v": 1.8648065105464209
                },
                {
                    "period": "2013-12-31",
                    "v": 6.551724137931035
                },
                {
                    "period": "2013-04-30",
                    "v": 1.777777777777778
                }
            ],
            "currentRatio": [
                {
                    "period": "2019-12-31",
                    "v": 1.8799
                },
                {
                    "period": "2018-12-31",
                    "v": 3.7264
                },
                {
                    "period": "2017-12-31",
                    "v": 3.1332
                },
                {
                    "period": "2016-12-31",
                    "v": 1.3286
                },
                {
                    "period": "2015-12-31",
                    "v": 5.1483
                },
                {
                    "period": "2014-12-31",
                    "v": 6.2898
                },
                {
                    "period": "2013-12-31",
                    "v": 7.2414
                },
                {
                    "period": "2013-04-30",
                    "v": 2.6667
                }
            ],
            "ebitPerShare": [
                {
                    "period": "2019-12-31",
                    "v": -1.1059
                },
                {
                    "period": "2018-12-31",
                    "v": -0.7746
                },
                {
                    "period": "2017-12-31",
                    "v": -0.5082
                },
                {
                    "period": "2016-12-31",
                    "v": -0.4635
                },
                {
                    "period": "2015-12-31",
                    "v": -0.4029
                },
                {
                    "period": "2014-12-31",
                    "v": -0.3029
                },
                {
                    "period": "2013-12-31",
                    "v": -0.1218
                },
                {
                    "period": "2013-04-30",
                    "v": -0.0395
                }
            ],
            "eps": [
                {
                    "period": "2019-12-31",
                    "v": -1.06
                },
                {
                    "period": "2018-12-31",
                    "v": -0.7734
                },
                {
                    "period": "2017-12-31",
                    "v": -0.5
                },
                {
                    "period": "2016-12-31",
                    "v": -0.4529
                },
                {
                    "period": "2015-12-31",
                    "v": -0.4148
                },
                {
                    "period": "2014-12-31",
                    "v": -0.3016
                },
                {
                    "period": "2013-12-31",
                    "v": -0.1218
                },
                {
                    "period": "2013-04-30",
                    "v": -0.0395
                }
            ],
            "grossMargin": [
                {
                    "period": "2019-12-31",
                    "v": 0.8951
                },
                {
                    "period": "2018-12-31",
                    "v": 0.8705
                },
                {
                    "period": "2017-12-31",
                    "v": 0.8927
                },
                {
                    "period": "2016-12-31",
                    "v": 0.8465
                },
                {
                    "period": "2015-12-31",
                    "v": 0.7917
                },
                {
                    "period": "2014-12-31",
                    "v": 0.8581
                },
                {
                    "period": "2013-12-31",
                    "v": 0.7241
                },
                {
                    "period": "2013-04-30",
                    "v": 1
                }
            ],
            "longtermDebtTotalAsset": [
                {
                    "period": "2019-12-31",
                    "v": 0.0125
                }
            ],
            "longtermDebtTotalCapital": [
                {
                    "period": "2019-12-31",
                    "v": 0.0218
                }
            ],
            "longtermDebtTotalEquity": [
                {
                    "period": "2019-12-31",
                    "v": 0.0223
                }
            ],
            "netDebtToTotalCapital": [
                {
                    "period": "2019-12-31",
                    "v": -0.5912
                },
                {
                    "period": "2018-12-31",
                    "v": -0.8205
                },
                {
                    "period": "2017-12-31",
                    "v": -0.1659
                },
                {
                    "period": "2016-12-31",
                    "v": -0.7309
                },
                {
                    "period": "2015-12-31",
                    "v": -0.1881
                },
                {
                    "period": "2014-12-31",
                    "v": -0.3411
                },
                {
                    "period": "2013-12-31",
                    "v": -0.9896
                },
                {
                    "period": "2013-04-30",
                    "v": -0.6957
                }
            ],
            "netDebtToTotalEquity": [
                {
                    "period": "2019-12-31",
                    "v": -0.605
                },
                {
                    "period": "2018-12-31",
                    "v": -0.8216
                },
                {
                    "period": "2017-12-31",
                    "v": -0.1659
                },
                {
                    "period": "2016-12-31",
                    "v": -0.7309
                },
                {
                    "period": "2015-12-31",
                    "v": -0.1881
                },
                {
                    "period": "2014-12-31",
                    "v": -0.3411
                },
                {
                    "period": "2013-12-31",
                    "v": -0.9896
                },
                {
                    "period": "2013-04-30",
                    "v": -0.6957
                }
            ],
            "netMargin": [
                {
                    "period": "2019-12-31",
                    "v": -0.9517
                },
                {
                    "period": "2018-12-31",
                    "v": -0.8148
                },
                {
                    "period": "2017-12-31",
                    "v": -0.6237
                },
                {
                    "period": "2016-12-31",
                    "v": -1.1876
                },
                {
                    "period": "2015-12-31",
                    "v": -1.9111
                },
                {
                    "period": "2014-12-31",
                    "v": -1.9257
                },
                {
                    "period": "2013-12-31",
                    "v": -2.4483
                },
                {
                    "period": "2013-04-30",
                    "v": -1.2778
                }
            ],
            "operatingMargin": [
                {
                    "period": "2019-12-31",
                    "v": -0.993
                },
                {
                    "period": "2018-12-31",
                    "v": -0.8161
                },
                {
                    "period": "2017-12-31",
                    "v": -0.6338
                },
                {
                    "period": "2016-12-31",
                    "v": -1.2154
                },
                {
                    "period": "2015-12-31",
                    "v": -1.8562
                },
                {
                    "period": "2014-12-31",
                    "v": -1.9343
                },
                {
                    "period": "2013-12-31",
                    "v": -2.4483
                },
                {
                    "period": "2013-04-30",
                    "v": -1.2778
                }
            ],
            "pretaxMargin": [
                {
                    "period": "2019-12-31",
                    "v": -0.9834
                },
                {
                    "period": "2018-12-31",
                    "v": -0.7983
                },
                {
                    "period": "2017-12-31",
                    "v": -0.615
                },
                {
                    "period": "2016-12-31",
                    "v": -1.181
                },
                {
                    "period": "2015-12-31",
                    "v": -1.8991
                },
                {
                    "period": "2014-12-31",
                    "v": -1.9231
                },
                {
                    "period": "2013-12-31",
                    "v": -2.4483
                },
                {
                    "period": "2013-04-30",
                    "v": -1.2778
                }
            ],
            "salesPerShare": [
                {
                    "period": "2019-12-31",
                    "v": 1.1138
                },
                {
                    "period": "2018-12-31",
                    "v": 0.9492
                },
                {
                    "period": "2017-12-31",
                    "v": 0.8017
                },
                {
                    "period": "2016-12-31",
                    "v": 0.3814
                },
                {
                    "period": "2015-12-31",
                    "v": 0.2171
                },
                {
                    "period": "2014-12-31",
                    "v": 0.1566
                },
                {
                    "period": "2013-12-31",
                    "v": 0.0497
                },
                {
                    "period": "2013-04-30",
                    "v": 0.0309
                }
            ],
            "sgaToSale": [
                {
                    "period": "2019-12-31",
                    "v": 0.1049
                },
                {
                    "period": "2018-12-31",
                    "v": 0.1295
                },
                {
                    "period": "2017-12-31",
                    "v": 0.1073
                },
                {
                    "period": "2016-12-31",
                    "v": 0.1535
                },
                {
                    "period": "2015-12-31",
                    "v": 0.2083
                },
                {
                    "period": "2014-12-31",
                    "v": 0.1419
                },
                {
                    "period": "2013-12-31",
                    "v": 0.2759
                },
                {
                    "period": "2013-04-30",
                    "v": 0
                }
            ],
            "totalDebtToEquity": [
                {
                    "period": "2019-12-31",
                    "v": 0.0232
                },
                {
                    "period": "2018-12-31",
                    "v": 0.0014
                },
                {
                    "period": "2017-12-31",
                    "v": 0
                },
                {
                    "period": "2016-12-31",
                    "v": 0
                },
                {
                    "period": "2015-12-31",
                    "v": 0
                },
                {
                    "period": "2014-12-31",
                    "v": 0
                },
                {
                    "period": "2013-12-31",
                    "v": 0
                },
                {
                    "period": "2013-04-30",
                    "v": 0
                }
            ],
            "totalDebtToTotalAsset": [
                {
                    "period": "2019-12-31",
                    "v": 0.0131
                },
                {
                    "period": "2018-12-31",
                    "v": 0.001
                },
                {
                    "period": "2017-12-31",
                    "v": 0
                },
                {
                    "period": "2016-12-31",
                    "v": 0
                },
                {
                    "period": "2015-12-31",
                    "v": 0
                },
                {
                    "period": "2014-12-31",
                    "v": 0
                },
                {
                    "period": "2013-12-31",
                    "v": 0
                },
                {
                    "period": "2013-04-30",
                    "v": 0
                }
            ],
            "totalDebtToTotalCapital": [
                {
                    "period": "2019-12-31",
                    "v": 0.0227
                },
                {
                    "period": "2018-12-31",
                    "v": 0.0014
                },
                {
                    "period": "2017-12-31",
                    "v": 0
                },
                {
                    "period": "2016-12-31",
                    "v": 0
                },
                {
                    "period": "2015-12-31",
                    "v": 0
                },
                {
                    "period": "2014-12-31",
                    "v": 0
                },
                {
                    "period": "2013-12-31",
                    "v": 0
                },
                {
                    "period": "2013-04-30",
                    "v": 0
                }
            ],
            "totalRatio": [
                {
                    "period": "2019-12-31",
                    "v": 2.2809
                },
                {
                    "period": "2018-12-31",
                    "v": 3.9376
                },
                {
                    "period": "2017-12-31",
                    "v": 3.2857
                },
                {
                    "period": "2016-12-31",
                    "v": 1.4334
                },
                {
                    "period": "2015-12-31",
                    "v": 5.3984
                },
                {
                    "period": "2014-12-31",
                    "v": 6.4667
                },
                {
                    "period": "2013-12-31",
                    "v": 7.5862
                },
                {
                    "period": "2013-04-30",
                    "v": 3.5556
                }
            ]
        }
    },
    "symbol": "BIM.ST"
}