{
    "metric": {
        "_10DayAverageTradingVolume": 0.01208,
        "_13WeekPriceReturnDaily": 3.5524,
        "_26WeekPriceReturnDaily": 6,
        "_3MonthAverageTradingVolume": 0.29227,
        "_52WeekHigh": 316.5,
        "_52WeekHighDate": "2020-09-17",
        "_52WeekLow": 257.5,
        "_52WeekLowDate": "2021-03-01",
        "_52WeekPriceReturnDaily": -0.34188,
        "_5DayPriceReturnDaily": 1.3913,
        "_assetTurnoverAnnual": 0.7683,
        "_assetTurnoverTTM": 0.71012,
        "_beta": 0.41035,
        "_bookValuePerShareAnnual": 77.38675,
        "_bookValuePerShareQuarterly": 80.77683,
        "_bookValueShareGrowth5Y": 4.80396,
        "_capitalSpendingGrowth5Y": 3.01089,
        "_cashFlowPerShareAnnual": 27.19066,
        "_cashFlowPerShareTTM": 24.62623,
        "_cashPerSharePerShareAnnual": 8.50725,
        "_cashPerSharePerShareQuarterly": 16.40083,
        "_currentDividendYieldTTM": 2.31561,
        "_currentEvfreeCashFlowAnnual": 31.32064,
        "_currentEvfreeCashFlowTTM": 47.63669,
        "_currentRatioAnnual": 1.04974,
        "_currentRatioQuarterly": 1.14106,
        "_dividendGrowthRate5Y": 5.49016,
        "_dividendPerShare5Y": null,
        "_dividendPerShareAnnual": 6.75,
        "_dividendYield5Y": null,
        "_dividendYieldIndicatedAnnual": 2.31561,
        "_dividendsPerShareTTM": 6.75,
        "_ebitdPerShareTTM": 31.2516,
        "_ebitdaCagr5Y": 10.24917,
        "_ebitdaInterimCagr5Y": null,
        "_epsBasicExclExtraItemsAnnual": 14.56358,
        "_epsBasicExclExtraItemsTTM": 12.54023,
        "_epsExclExtraItemsAnnual": 14.56358,
        "_epsExclExtraItemsTTM": 12.54023,
        "_epsGrowth3Y": 8.01472,
        "_epsGrowth5Y": 10.78616,
        "_epsGrowthQuarterlyYoy": -15.22995,
        "_epsGrowthTTMYoy": -16.25135,
        "_epsInclExtraItemsAnnual": 14.56358,
        "_epsInclExtraItemsTTM": 12.54023,
        "_epsNormalizedAnnual": 15.12148,
        "_focfCagr5Y": 6.04875,
        "_freeCashFlowAnnual": 6842,
        "_freeCashFlowPerShareTTM": 3.28634,
        "_freeCashFlowTTM": 2308,
        "_freeOperatingCashFlowrevenue5Y": 5.4346,
        "_freeOperatingCashFlowrevenueTTM": 1.98744,
        "_grossMargin5Y": 29.72539,
        "_grossMarginAnnual": 32.54156,
        "_grossMarginTTM": 31.9567,
        "_inventoryTurnoverAnnual": 5.11232,
        "_inventoryTurnoverTTM": 4.40126,
        "_longTermDebtequityAnnual": 70.2826,
        "_longTermDebtequityQuarterly": 75.2666,
        "_marketCapitalization": 205181.3,
        "_monthToDatePriceReturnDaily": 2.2807,
        "_netDebtAnnual": 40121,
        "_netDebtInterim": 45506,
        "_netIncomeEmployeeAnnual": 255192,
        "_netIncomeEmployeeTTM": 222550.1,
        "_netInterestCoverageAnnual": 20.78718,
        "_netInterestCoverageTTM": 24.93144,
        "_netMarginGrowth5Y": 7.64042,
        "_netProfitMargin5Y": 7.51005,
        "_netProfitMarginAnnual": 9.6483,
        "_netProfitMarginTTM": 8.83156,
        "_operatingMargin5Y": 10.82901,
        "_operatingMarginAnnual": 13.76404,
        "_operatingMarginTTM": 12.55328,
        "_payoutRatioAnnual": 46.35315,
        "_payoutRatioTTM": 53.83218,
        "_pbAnnual": 3.76679,
        "_pbQuarterly": 3.60871,
        "_pcfShareTTM": 11.86362,
        "_peBasicExclExtraTTM": 22.72686,
        "_peExclExtraAnnual": 20.01568,
        "_peExclExtraHighTTM": 27.69481,
        "_peExclExtraTTM": 23.24519,
        "_peExclLowTTM": 18.3987,
        "_peInclExtraTTM": 23.24519,
        "_peNormalizedAnnual": 19.27721,
        "_pfcfShareAnnual": 29.98849,
        "_pfcfShareTTM": 88.90003,
        "_pretaxMargin5Y": 9.89047,
        "_pretaxMarginAnnual": 12.9772,
        "_pretaxMarginTTM": 11.95825,
        "_priceRelativeToSP50013Week": null,
        "_priceRelativeToSP50026Week": null,
        "_priceRelativeToSP5004Week": null,
        "_priceRelativeToSP50052Week": null,
        "_priceRelativeToSP500Ytd": null,
        "_psAnnual": 1.68524,
        "_psTTM": 1.76684,
        "_ptbvAnnual": 59.40396,
        "_ptbvQuarterly": 43.62774,
        "_quickRatioAnnual": 0.65096,
        "_quickRatioQuarterly": 0.74512,
        "_receivablesTurnoverAnnual": 6.46088,
        "_receivablesTurnoverTTM": 6.31926,
        "_revenueEmployeeAnnual": 2644943,
        "_revenueEmployeeTTM": 2519942,
        "_revenueGrowth3Y": 3.67284,
        "_revenueGrowth5Y": 4.32568,
        "_revenueGrowthQuarterlyYoy": 1.97487,
        "_revenueGrowthTTMYoy": -9.53572,
        "_revenuePerShareAnnual": 173.3618,
        "_revenuePerShareTTM": 165.3553,
        "_revenueShareGrowth5Y": 4.32694,
        "_roaRfy": 7.41276,
        "_roaa5Y": 6.10752,
        "_roae5Y": 17.40955,
        "_roaeTTM": 15.7251,
        "_roeRfy": 18.85745,
        "_roeTTM": 6.27144,
        "_roi5Y": 9.03398,
        "_roiAnnual": 10.93146,
        "_roiTTM": 9.29647,
        "_tangibleBookValuePerShareAnnual": 4.91783,
        "_tangibleBookValuePerShareQuarterly": 6.69616,
        "_tbvCagr5Y": -29.77442,
        "_totalDebtCagr5Y": 7.11812,
        "_totalDebttotalEquityAnnual": 84.81013,
        "_totalDebttotalEquityQuarterly": 100.5147,
        "_yearToDatePriceReturnDaily": 7.7634
    },
    "metricType": "all",
    "series": {
        "annual": {
            "cashRatio": [
                {
                    "period": "2019-12-31",
                    "v": 0.05348890942698706
                },
                {
                    "period": "2018-12-31",
                    "v": 0.06280669681516406
                },
                {
                    "period": "2017-12-31",
                    "v": 0.09189469659730189
                },
                {
                    "period": "2016-12-31",
                    "v": 0.08822900436867992
                },
                {
                    "period": "2015-12-31",
                    "v": 0.0617316519812167
                }
            ],
            "currentRatio": [
                {
                    "period": "2019-12-31",
                    "v": 0.97
                },
                {
                    "period": "2018-12-31",
                    "v": 1.0138
                },
                {
                    "period": "2017-12-31",
                    "v": 1.0901
                },
                {
                    "period": "2016-12-31",
                    "v": 1.0996
                },
                {
                    "period": "2015-12-31",
                    "v": 1.2426
                }
            ],
            "ebitPerShare": [
                {
                    "period": "2019-12-31",
                    "v": 20.4314
                },
                {
                    "period": "2018-12-31",
                    "v": 15.3197
                },
                {
                    "period": "2017-12-31",
                    "v": 16.9514
                },
                {
                    "period": "2016-12-31",
                    "v": 12.8257
                },
                {
                    "period": "2015-12-31",
                    "v": 13.7881
                }
            ],
            "eps": [
                {
                    "period": "2019-12-31",
                    "v": 13.1226
                },
                {
                    "period": "2018-12-31",
                    "v": 11.2288
                },
                {
                    "period": "2017-12-31",
                    "v": 11.5563
                },
                {
                    "period": "2016-12-31",
                    "v": 5.4105
                },
                {
                    "period": "2015-12-31",
                    "v": 8.7265
                }
            ],
            "grossMargin": [
                {
                    "period": "2019-12-31",
                    "v": 0.2954
                },
                {
                    "period": "2018-12-31",
                    "v": 0.2822
                },
                {
                    "period": "2017-12-31",
                    "v": 0.2962
                },
                {
                    "period": "2016-12-31",
                    "v": 0.2845
                },
                {
                    "period": "2015-12-31",
                    "v": 0.2702
                }
            ],
            "longtermDebtTotalAsset": [
                {
                    "period": "2019-12-31",
                    "v": 0.2462
                },
                {
                    "period": "2018-12-31",
                    "v": 0.2816
                },
                {
                    "period": "2017-12-31",
                    "v": 0.3238
                },
                {
                    "period": "2016-12-31",
                    "v": 0.2737
                },
                {
                    "period": "2015-12-31",
                    "v": 0.185
                }
            ],
            "longtermDebtTotalCapital": [
                {
                    "period": "2019-12-31",
                    "v": 0.3793
                },
                {
                    "period": "2018-12-31",
                    "v": 0.4321
                },
                {
                    "period": "2017-12-31",
                    "v": 0.4951
                },
                {
                    "period": "2016-12-31",
                    "v": 0.4558
                },
                {
                    "period": "2015-12-31",
                    "v": 0.282
                }
            ],
            "longtermDebtTotalEquity": [
                {
                    "period": "2019-12-31",
                    "v": 0.7383
                },
                {
                    "period": "2018-12-31",
                    "v": 0.9215
                },
                {
                    "period": "2017-12-31",
                    "v": 1.1257
                },
                {
                    "period": "2016-12-31",
                    "v": 0.9419
                },
                {
                    "period": "2015-12-31",
                    "v": 0.4964
                }
            ],
            "netDebtToTotalCapital": [
                {
                    "period": "2019-12-31",
                    "v": 0.4643
                },
                {
                    "period": "2018-12-31",
                    "v": 0.5051
                },
                {
                    "period": "2017-12-31",
                    "v": 0.5251
                },
                {
                    "period": "2016-12-31",
                    "v": 0.474
                },
                {
                    "period": "2015-12-31",
                    "v": 0.401
                }
            ],
            "netDebtToTotalEquity": [
                {
                    "period": "2019-12-31",
                    "v": 0.9037
                },
                {
                    "period": "2018-12-31",
                    "v": 1.0773
                },
                {
                    "period": "2017-12-31",
                    "v": 1.1939
                },
                {
                    "period": "2016-12-31",
                    "v": 0.9794
                },
                {
                    "period": "2015-12-31",
                    "v": 0.7059
                }
            ],
            "netMargin": [
                {
                    "period": "2019-12-31",
                    "v": 0.0715
                },
                {
                    "period": "2018-12-31",
                    "v": 0.0665
                },
                {
                    "period": "2017-12-31",
                    "v": 0.0743
                },
                {
                    "period": "2016-12-31",
                    "v": 0.0375
                },
                {
                    "period": "2015-12-31",
                    "v": 0.0622
                }
            ],
            "operatingMargin": [
                {
                    "period": "2019-12-31",
                    "v": 0.1113
                },
                {
                    "period": "2018-12-31",
                    "v": 0.0908
                },
                {
                    "period": "2017-12-31",
                    "v": 0.109
                },
                {
                    "period": "2016-12-31",
                    "v": 0.089
                },
                {
                    "period": "2015-12-31",
                    "v": 0.0983
                }
            ],
            "pretaxMargin": [
                {
                    "period": "2019-12-31",
                    "v": 0.1011
                },
                {
                    "period": "2018-12-31",
                    "v": 0.081
                },
                {
                    "period": "2017-12-31",
                    "v": 0.0981
                },
                {
                    "period": "2016-12-31",
                    "v": 0.0807
                },
                {
                    "period": "2015-12-31",
                    "v": 0.0899
                }
            ],
            "salesPerShare": [
                {
                    "period": "2019-12-31",
                    "v": 183.6466
                },
                {
                    "period": "2018-12-31",
                    "v": 168.7313
                },
                {
                    "period": "2017-12-31",
                    "v": 155.5817
                },
                {
                    "period": "2016-12-31",
                    "v": 144.1434
                },
                {
                    "period": "2015-12-31",
                    "v": 140.272
                }
            ],
            "sgaToSale": [
                {
                    "period": "2019-12-31",
                    "v": 0.7046
                },
                {
                    "period": "2018-12-31",
                    "v": 0.7178
                },
                {
                    "period": "2017-12-31",
                    "v": 0.7038
                },
                {
                    "period": "2016-12-31",
                    "v": 0.7155
                },
                {
                    "period": "2015-12-31",
                    "v": 0.7298
                }
            ],
            "totalDebtToEquity": [
                {
                    "period": "2019-12-31",
                    "v": 0.9465
                },
                {
                    "period": "2018-12-31",
                    "v": 1.1327
                },
                {
                    "period": "2017-12-31",
                    "v": 1.2735
                },
                {
                    "period": "2016-12-31",
                    "v": 1.0664
                },
                {
                    "period": "2015-12-31",
                    "v": 0.7604
                }
            ],
            "totalDebtToTotalAsset": [
                {
                    "period": "2019-12-31",
                    "v": 0.3156
                },
                {
                    "period": "2018-12-31",
                    "v": 0.3461
                },
                {
                    "period": "2017-12-31",
                    "v": 0.3663
                },
                {
                    "period": "2016-12-31",
                    "v": 0.3098
                },
                {
                    "period": "2015-12-31",
                    "v": 0.2834
                }
            ],
            "totalDebtToTotalCapital": [
                {
                    "period": "2019-12-31",
                    "v": 0.4862
                },
                {
                    "period": "2018-12-31",
                    "v": 0.5311
                },
                {
                    "period": "2017-12-31",
                    "v": 0.5601
                },
                {
                    "period": "2016-12-31",
                    "v": 0.5161
                },
                {
                    "period": "2015-12-31",
                    "v": 0.4319
                }
            ],
            "totalRatio": [
                {
                    "period": "2019-12-31",
                    "v": 1.5004
                },
                {
                    "period": "2018-12-31",
                    "v": 1.4401
                },
                {
                    "period": "2017-12-31",
                    "v": 1.4038
                },
                {
                    "period": "2016-12-31",
                    "v": 1.4095
                },
                {
                    "period": "2015-12-31",
                    "v": 1.594
                }
            ]
        }
    },
    "symbol": "ESSITY B.ST"
}