[
    {
        "Date": "2000-03-31T00:00:00.000Z",
        "Dividends": 11.0
    },
    {
        "Date": "2001-04-04T00:00:00.000Z",
        "Dividends": 4.5
    },
    {
        "Date": "2002-04-04T00:00:00.000Z",
        "Dividends": 2.25
    },
    {
        "Date": "2003-04-11T00:00:00.000Z",
        "Dividends": 2.75
    },
    {
        "Date": "2005-04-05T00:00:00.000Z",
        "Dividends": 4.5
    },
    {
        "Date": "2006-04-06T00:00:00.000Z",
        "Dividends": 15.5
    },
    {
        "Date": "2007-04-12T00:00:00.000Z",
        "Dividends": 8.0
    },
    {
        "Date": "2008-04-09T00:00:00.000Z",
        "Dividends": 11.0
    },
    {
        "Date": "2009-04-08T00:00:00.000Z",
        "Dividends": 4.0
    },
    {
        "Date": "2010-04-15T00:00:00.000Z",
        "Dividends": 6.0
    },
    {
        "Date": "2011-04-14T00:00:00.000Z",
        "Dividends": 10.0
    },
    {
        "Date": "2012-04-05T00:00:00.000Z",
        "Dividends": 10.0
    },
    {
        "Date": "2013-04-10T00:00:00.000Z",
        "Dividends": 10.0
    },
    {
        "Date": "2014-04-03T00:00:00.000Z",
        "Dividends": 6.0
    },
    {
        "Date": "2014-10-24T00:00:00.000Z",
        "Dividends": 6.0
    },
    {
        "Date": "2014-10-27T00:00:00.000Z",
        "Dividends": 6.0
    },
    {
        "Date": "2015-03-25T00:00:00.000Z",
        "Dividends": 6.0
    },
    {
        "Date": "2015-10-26T00:00:00.000Z",
        "Dividends": 6.0
    },
    {
        "Date": "2016-11-04T00:00:00.000Z",
        "Dividends": 3.0
    },
    {
        "Date": "2017-04-06T00:00:00.000Z",
        "Dividends": 3.0
    },
    {
        "Date": "2017-11-03T00:00:00.000Z",
        "Dividends": 5.0
    },
    {
        "Date": "2018-04-12T00:00:00.000Z",
        "Dividends": 4.0
    },
    {
        "Date": "2018-11-02T00:00:00.000Z",
        "Dividends": 4.0
    },
    {
        "Date": "2019-04-10T00:00:00.000Z",
        "Dividends": 2.0
    },
    {
        "Date": "2019-11-04T00:00:00.000Z",
        "Dividends": 2.0
    },
    {
        "Date": "2020-04-02T00:00:00.000Z",
        "Dividends": 2.5
    },
    {
        "Date": "2020-10-30T00:00:00.000Z",
        "Dividends": 2.5
    },
    {
        "Date": "2020-11-13T00:00:00.000Z",
        "Dividends": 2.5
    },
    {
        "Date": "2021-03-31T00:00:00.000Z",
        "Dividends": 2.5
    }
]