[
    {
        "adjustedAmount": 0.54,
        "amount": 0.54,
        "currency": "SEK",
        "date": "2016-05-18",
        "declarationDate": "2016-02-25",
        "payDate": "2016-05-24",
        "recordDate": "2016-05-19",
        "symbol": "ATT.ST"
    },
    {
        "adjustedAmount": 1.22,
        "amount": 1.22,
        "currency": "SEK",
        "date": "2017-04-07",
        "declarationDate": "2017-02-15",
        "payDate": "2017-04-13",
        "recordDate": "2017-04-10",
        "symbol": "ATT.ST"
    },
    {
        "adjustedAmount": 1.27,
        "amount": 1.27,
        "currency": "SEK",
        "date": "2018-04-13",
        "declarationDate": "2018-02-15",
        "payDate": "2018-04-19",
        "recordDate": "2018-04-16",
        "symbol": "ATT.ST"
    },
    {
        "adjustedAmount": 0.6,
        "amount": 0.6,
        "currency": "SEK",
        "date": "2019-04-12",
        "declarationDate": "2019-02-14",
        "payDate": "2019-04-18",
        "recordDate": "2019-04-15",
        "symbol": "ATT.ST"
    }
]