[
    {
        "adjustedAmount": 2.2670585642,
        "amount": 0.25,
        "currency": "SEK",
        "date": "2012-04-26",
        "declarationDate": "2012-02-07",
        "payDate": "2012-05-04",
        "recordDate": "2012-04-30",
        "symbol": "BEGR.ST"
    },
    {
        "adjustedAmount": 1.75,
        "amount": 1.75,
        "currency": "SEK",
        "date": "2019-04-26",
        "declarationDate": "2019-01-31",
        "payDate": "2019-05-03",
        "recordDate": "2019-04-29",
        "symbol": "BEGR.ST"
    }
]