{
    "address": "Heliosgatan 3",
    "city": "Stockholm",
    "country": "SE",
    "currency": "SEK",
    "cusip": "W3164D102",
    "description": "Firefly AB engages in the supply of spark detection, fire, and dust explosion protection systems. The company is headquartered in Stockholm, Stockholm and currently employs 57 full-time employees. The company went IPO on 2000-06-26. The Company\u2019s activities are structured into two principal business areas: Industrial Applications and Infra systems (Sentio). The Industrial applications area includes customized fire prevention systems, which monitor industrial processes in such industries as woodworking, tissue, food, bioenergy, tobacco and recycling, among others. The firm's solutions include Quick Suppression System, Spark Detection System and a range of extinguishing methods. The Infrastructure systems business area includes fire monitoring of tunnels, including subway, train, road and cable tunnels, by means of multiple gas detection (MGD) or electronic nose. The firm offers its solutions worldwide.",
    "employeeTotal": "57.0",
    "exchange": "NASDAQ OMX NORDIC",
    "finnhubIndustry": "Electrical Equipment",
    "ggroup": "Technology Hardware & Equipment",
    "gind": "Electronic Equipment, Instruments & Components",
    "gsector": "Information Technology",
    "gsubind": "Electronic Equipment & Instruments ",
    "ipo": "2000-06-26",
    "isin": "SE0000395428",
    "logo": "https://finnhub.io/api/logo?symbol=FIRE.ST",
    "marketCapitalization": 429.7002,
    "naics": "Communications Equipment Manufacturing",
    "naicsNationalIndustry": "Other Communications Equipment Manufacturing",
    "naicsSector": "Manufacturing",
    "naicsSubsector": "Computer and Electronic Product Manufacturing",
    "name": "Firefly AB",
    "phone": "4684492500.0",
    "sedol": "5246360",
    "shareOutstanding": 6.0014,
    "state": "STOCKHOLM",
    "ticker": "FIRE.ST",
    "weburl": "http://www.firefly.se/"
}