{
    "address": "Torggatan 13",
    "city": "Solna",
    "country": "SE",
    "currency": "SEK",
    "cusip": "W46571100",
    "description": "Qleanair Holding AB supplies premium solutions within the air cleaning market for indoor environments. The company is headquartered in Solna, Stockholm and currently employs 106 full-time employees. The company went IPO on 2019-12-12. Its offering consists of long-term full-service contracts encompassing clean air technology, hardware solutions, installation and maintenance. The Company\u2019s technology platform, with proprietary filters and back-office technology, enable a differentiated portfolio of turn-key products, such as smoking cabins, air cleaner for different kind of facilities and solutions for clean and sterile environments. The firm addresses the need of a variety of customers, including workspaces, public spaces, industries and cleanrooms. The company is active globally.",
    "employeeTotal": "106.0",
    "exchange": "NASDAQ OMX NORDIC",
    "finnhubIndustry": "Commercial Services & Supplies",
    "ggroup": "Commercial  & Professional Services",
    "gind": "Commercial Services & Supplies",
    "gsector": "Industrials",
    "gsubind": "Diversified Support Services",
    "ipo": "2019-12-12",
    "isin": "SE0013382066",
    "logo": "",
    "marketCapitalization": 962.8762,
    "naics": "Management, Scientific, and Technical Consulting Services",
    "naicsNationalIndustry": "Environmental Consulting Services",
    "naicsSector": "Professional, Scientific, and Technical Services",
    "naicsSubsector": "Professional, Scientific, and Technical Services",
    "name": "Qleanair Holding AB",
    "phone": "46854578800.0",
    "sedol": "BKM67Q0",
    "shareOutstanding": 14.8592,
    "state": "STOCKHOLM",
    "ticker": "QAIR.ST",
    "weburl": "https://www.qleanair.com/"
}